odoo/addons/mrp_lot_on_hand_first/README.rst
odoo/addons/mrp_lot_on_hand_first/__init__.py
odoo/addons/mrp_lot_on_hand_first/__manifest__.py
odoo/addons/mrp_lot_on_hand_first/i18n/es.po
odoo/addons/mrp_lot_on_hand_first/i18n/fr.po
odoo/addons/mrp_lot_on_hand_first/i18n/it.po
odoo/addons/mrp_lot_on_hand_first/i18n/mrp_lot_on_hand_first.pot
odoo/addons/mrp_lot_on_hand_first/models/__init__.py
odoo/addons/mrp_lot_on_hand_first/models/mrp_production.py
odoo/addons/mrp_lot_on_hand_first/readme/CONTRIBUTORS.rst
odoo/addons/mrp_lot_on_hand_first/readme/DESCRIPTION.rst
odoo/addons/mrp_lot_on_hand_first/static/description/icon.png
odoo/addons/mrp_lot_on_hand_first/static/description/index.html
odoo/addons/mrp_lot_on_hand_first/views/mrp_production.xml
odoo/addons/mrp_lot_on_hand_first/views/stock_picking_type.xml
odoo14_addon_mrp_lot_on_hand_first-14.0.1.0.1.dev11.dist-info/METADATA
odoo14_addon_mrp_lot_on_hand_first-14.0.1.0.1.dev11.dist-info/WHEEL
odoo14_addon_mrp_lot_on_hand_first-14.0.1.0.1.dev11.dist-info/top_level.txt
odoo14_addon_mrp_lot_on_hand_first-14.0.1.0.1.dev11.dist-info/RECORD
